async_okta_jwt/__init__.py
async_okta_jwt/exceptions.py
async_okta_jwt/jwt.py
async_okta_jwt/utils.py
async_okta_jwt-1.3.5.1.dist-info/LICENSE
async_okta_jwt-1.3.5.1.dist-info/METADATA
async_okta_jwt-1.3.5.1.dist-info/WHEEL
async_okta_jwt-1.3.5.1.dist-info/top_level.txt
async_okta_jwt-1.3.5.1.dist-info/RECORD
