Metadata-Version: 2.1
Name: async-okta-jwt
Version: 1.3.5.1
Summary: Okta JWT Access Token verifier
Home-page: https://github.com/ypukhta/okta_jwt
Author: Adithya Sampatoor, Yevgen Pukhta
Author-email: adithya.sampatoor@gmail.com, eugene.pukhta@gmail.com
License: UNKNOWN
Platform: UNKNOWN
Classifier: Development Status :: 5 - Production/Stable
Classifier: Intended Audience :: Developers
Classifier: Natural Language :: English
Classifier: License :: OSI Approved :: MIT License
Classifier: Programming Language :: Python :: 3.7
Classifier: Programming Language :: Python :: Implementation :: PyPy
Classifier: Topic :: Utilities
License-File: LICENSE
Requires-Dist: six (<2.0)
Requires-Dist: httpx
Requires-Dist: python-jose
